netbox_task/__init__.py
netbox_task/navigation.py
netbox_task/template_content.py
netbox_task/urls.py
netbox_task/api/__init__.py
netbox_task/api/serializers.py
netbox_task/api/urls.py
netbox_task/api/views.py
netbox_task/forms/__init__.py
netbox_task/forms/awx_server_forms.py
netbox_task/forms/awx_template_forms.py
netbox_task/forms/virtual_machine_button_forms.py
netbox_task/migrations/0001_initial.py
netbox_task/migrations/__init__.py
netbox_task/models/__init__.py
netbox_task/models/awx.py
netbox_task/models/virtualmachine_buttons.py
netbox_task/tables/__init__.py
netbox_task/tables/awx_server.py
netbox_task/tables/awx_template.py
netbox_task/tables/virtualmachine_buttons.py
netbox_task/templates/netbox_task/awxserver.html
netbox_task/templates/netbox_task/awxtemplate.html
netbox_task/templates/netbox_task/virtualmachinebuttons.html
netbox_task/templates/netbox_task/inc/virtual_machine_addition_button.html
netbox_task/templatetags/__init__.py
netbox_task/templatetags/virtualmachine_buttons.py
netbox_task/views/__init__.py
netbox_task/views/awx_server.py
netbox_task/views/awx_template.py
netbox_task/views/virtualmachine_buttons.py
netbox_task-1.0.2.dist-info/LICENSE
netbox_task-1.0.2.dist-info/METADATA
netbox_task-1.0.2.dist-info/WHEEL
netbox_task-1.0.2.dist-info/entry_points.txt
netbox_task-1.0.2.dist-info/top_level.txt
netbox_task-1.0.2.dist-info/RECORD
